MANIFEST.in
README.md
build.py
requirements-dev.txt
requirements.txt
setup.py
market_break/__init__.py
market_break/dataset.py
market_break/evaluation.py
market_break/experiment.py
market_break/interval.py
market_break/process.py
market_break/visualize.py
market_break.egg-info/PKG-INFO
market_break.egg-info/SOURCES.txt
market_break.egg-info/dependency_links.txt
market_break.egg-info/requires.txt
market_break.egg-info/top_level.txt
market_break/utils/base.py